LICENSE.txt
README.md
setup.py
hypercorn_api/__init__.py
hypercorn_api/hypercorn_api.py
hypercorn_api/utilities.py
hypercorn_api.egg-info/PKG-INFO
hypercorn_api.egg-info/SOURCES.txt
hypercorn_api.egg-info/dependency_links.txt
hypercorn_api.egg-info/requires.txt
hypercorn_api.egg-info/top_level.txt