Metadata-Version: 2.1
Name: hypercorn_api
Version: 0.2.0
Summary: HyperCornAPI powerful api for image and spectrum processing.
Home-page: https://github.com/HyperCorn/HyperCornAPI-Python-Wrapper
Download-URL: https://github.com/HyperCorn/HyperCornAPI-Python-Wrapper/releases/tag/0.2.0
Author: HyperCorn
Author-email: hypercorncordoba@gmail.com
Keywords: IMAGES,SPECTRUMS,CROPS
Classifier: Development Status :: 5 - Production/Stable
Classifier: Intended Audience :: Developers
Classifier: License :: OSI Approved :: MIT License
Classifier: Programming Language :: Python :: 3
License-File: LICENSE.txt
Requires-Dist: requests
